django_ldapdb_pyldap-0.4.1.dist-info/top_level.txt
django_ldapdb_pyldap-0.4.1.dist-info/METADATA
django_ldapdb_pyldap-0.4.1.dist-info/WHEEL
django_ldapdb_pyldap-0.4.1.dist-info/RECORD
django_ldapdb_pyldap-0.4.1.dist-info/metadata.json
django_ldapdb_pyldap-0.4.1.dist-info/DESCRIPTION.rst
ldapdb/__init__.py
ldapdb/router.py
ldapdb/tests.py
ldapdb/backends/__init__.py
ldapdb/backends/ldap/base.py
ldapdb/backends/ldap/__init__.py
ldapdb/backends/ldap/compiler.py
ldapdb/models/fields.py
ldapdb/models/base.py
ldapdb/models/__init__.py
