Metadata-Version: 2.0
Name: django-ldapdb-pyldap
Version: 0.4.1
Summary: An LDAP database backend for Django
Home-page: https://github.com/jlaine/django-ldapdb
Author: Jeremy Laine
Author-email: jeremy.laine@m4x.org
License: UNKNOWN
Keywords: django,ldap,database
Platform: UNKNOWN
Classifier: Development Status :: 5 - Production/Stable
Classifier: Environment :: Web Environment
Classifier: Programming Language :: Python
Classifier: Framework :: Django
Classifier: Intended Audience :: Developers
Classifier: Intended Audience :: System Administrators
Classifier: Topic :: Internet :: WWW/HTTP
Classifier: Topic :: System :: Systems Administration :: Authentication/Directory :: LDAP
Classifier: Topic :: Software Development :: Libraries :: Python Modules
Requires-Dist: django (>=1.2)
Requires-Dist: pyldap (>=2.4.25)
